cathd/CathD.py
cathd/__init__.py
cathd/utils.py
CathD-0.0.6.dist-info/LICENSE
CathD-0.0.6.dist-info/METADATA
CathD-0.0.6.dist-info/WHEEL
CathD-0.0.6.dist-info/top_level.txt
CathD-0.0.6.dist-info/RECORD
