Metadata-Version: 2.1
Name: CathD
Version: 0.0.6
Summary: Library used to download files and support sending to S3
Author: ryyos (Rio Dwi Saputra)
Author-email: <riodwi12174@gmail.com>
Keywords: download,s3,s3fs,log
Classifier: Development Status :: 1 - Planning
Classifier: Intended Audience :: Developers
Classifier: Programming Language :: Python
Classifier: Operating System :: Microsoft :: Windows
License-File: LICENSE
Requires-Dist: requests
Requires-Dist: s3fs
Requires-Dist: tqdm
Requires-Dist: loguru
